{"victory_district": 3, "county": "Bristol", "delta_local_aid": -778461.001, "state_senator": "Mark C. Montigny  ( D )", "established": 1860, "votes": {"Patrick": 2061, "Baker": 1487, "Total": 3980, "Stein": 33, "Cahill": 399}, "unemployment_percentage": 9.6, "registered_voters": {"Unenrolled": 4295, "Green-Rainbow": 6, "Republican": 562, "Democrat": 2587, "Total": 7478}, "local_aid_2013": 1282445.0, "percent_registered_unenrolled": 57.43514309, "media_market": "Providence", "delta_local_aid_per_capita": -75.55673115, "unemployment_total": 558, "unemployment_difference_from_MA_average": 2.9, "registered_percentages": {"% Republican": 7.515378443, "% Democrat": 34.59481145, "% Green-Rainbow": 0.080235357, "% Unenrolled": 57.43514309}, "percent_registered_republicans": 7.515378443, "delta_local_aid_percentage": -41.25267088, "slug": "acushnet", "federal_reps": "William Keating (D)", "population": 10303, "image_link": "http://upload.wikimedia.org/wikipedia/commons/thumb/a/ae/Acushnet_ma_highlight.png/250px-Acushnet_ma_highlight.png", "name": "acushnet", "gov_type": "open town meeting", "vote_percentages": {"% Cahill": 10.02512563, "% Patrick": 51.7839196, "% Baker": 37.36180905, "% Stein": 0.829145729}, "local_aid_2008": 2060906.001}