{"established": 1732, "votes": {"Patrick": 1263, "Baker": 2052, "Total": 3718, "Stein": 54, "Cahill": 349}, "name": "dudley", "gov_type": "open town meeting", "unemployment_percentage": 7.5, "image_link": "http://upload.wikimedia.org/wikipedia/commons/thumb/6/63/Dudley_ma_highlight.png/250px-Dudley_ma_highlight.png", "delta_local_aid": -586851.6571, "unemployment_total": 458, "registered_voters": {"Unenrolled": 4326, "Green-Rainbow": 10, "Republican": 902, "Democrat": 1858, "Total": 7145}, "county": "Worcester", "local_aid_2013": 1511226.0, "vote_percentages": {"% Cahill": 9.386767079, "% Patrick": 33.96987628, "% Baker": 55.19096288, "% Stein": 1.45239376}, "unemployment_difference_from_MA_average": 0.8, "local_aid_2008": 2098077.657, "registered_percentages": {"% Republican": 12.62421274, "% Democrat": 26.00419874, "% Green-Rainbow": 0.139958013, "% Unenrolled": 60.54583625}, "percent_registered_republicans": 12.62421274, "percent_registered_unenrolled": 60.54583625, "delta_local_aid_percentage": -30.5478164, "slug": "dudley", "delta_local_aid_per_capita": -51.52341151, "population": 11390}