{"established": 1671, "votes": {"Patrick": 965, "Baker": 807, "Total": 1948, "Stein": 31, "Cahill": 145}, "name": "edgartown", "gov_type": "open town meeting", "unemployment_percentage": 12.0, "image_link": "http://upload.wikimedia.org/wikipedia/commons/thumb/8/82/Seal_of_Massachusetts.svg/200px-Seal_of_Massachusetts.svg.png", "delta_local_aid": -34200.74921, "unemployment_total": 307, "registered_voters": {"Unenrolled": 1722, "Green-Rainbow": 2, "Republican": 472, "Democrat": 1088, "Total": 3293}, "county": "Dukes", "local_aid_2013": 56341.0, "vote_percentages": {"% Cahill": 7.443531828, "% Patrick": 49.53798768, "% Baker": 41.42710472, "% Stein": 1.59137577}, "unemployment_difference_from_MA_average": 5.3, "local_aid_2008": 90541.74921, "registered_percentages": {"% Republican": 14.33343456, "% Democrat": 33.03978135, "% Green-Rainbow": 0.060734892, "% Unenrolled": 52.29274218}, "percent_registered_republicans": 14.33343456, "percent_registered_unenrolled": 52.29274218, "delta_local_aid_percentage": -41.25343676, "slug": "edgartown", "delta_local_aid_per_capita": -8.409331009, "population": 4067}