{"victory_district": 3, "county": "Plymouth", "delta_local_aid": -1088075.368, "state_senator": "Robert L. Hedlund ( R )", "established": 1644, "votes": {"Patrick": 2245, "Baker": 1831, "Total": 4651, "Stein": 79, "Cahill": 496}, "unemployment_percentage": 6.7, "registered_voters": {"Unenrolled": 4449, "Green-Rainbow": 9, "Republican": 912, "Democrat": 2792, "Total": 8211}, "local_aid_2013": 1792503.0, "percent_registered_unenrolled": 54.1834125, "media_market": "Boston", "delta_local_aid_per_capita": -105.7102272, "unemployment_total": 394, "unemployment_difference_from_MA_average": 0.0, "registered_percentages": {"% Republican": 11.10705152, "% Democrat": 34.00316648, "% Green-Rainbow": 0.109609061, "% Unenrolled": 54.1834125}, "percent_registered_republicans": 11.10705152, "delta_local_aid_percentage": -41.25272858, "slug": "hull", "federal_reps": "Stephen Lynch (D)", "population": 10293, "image_link": "http://upload.wikimedia.org/wikipedia/commons/thumb/c/c5/Hull_ma_highlight.png/250px-Hull_ma_highlight.png", "name": "hull", "gov_type": "open town meeting", "vote_percentages": {"% Cahill": 10.66437325, "% Patrick": 48.26918942, "% Baker": 39.36787788, "% Stein": 1.69855945}, "local_aid_2008": 2880578.368}