{"victory_district": 2, "county": "Essex", "delta_local_aid": -1883633.783, "state_senator": "Thomas M. McGee ( D )", "established": 1815, "votes": {"Patrick": 3065, "Baker": 5538, "Total": 9886, "Stein": 103, "Cahill": 1180}, "unemployment_percentage": 6.6, "registered_voters": {"Unenrolled": 10159, "Green-Rainbow": 15, "Republican": 1795, "Democrat": 5987, "Total": 18024}, "local_aid_2013": 3103116.0, "percent_registered_unenrolled": 56.36373724, "media_market": "Boston", "delta_local_aid_per_capita": -70.73883819, "unemployment_total": 974, "unemployment_difference_from_MA_average": -0.1, "registered_percentages": {"% Republican": 9.958943631, "% Democrat": 33.21682202, "% Green-Rainbow": 0.08322237, "% Unenrolled": 56.36373724}, "percent_registered_republicans": 9.958943631, "delta_local_aid_percentage": -41.25269149, "slug": "saugus", "federal_reps": "John Tierney (D)", "population": 26628, "image_link": "http://upload.wikimedia.org/wikipedia/commons/thumb/7/7b/Saugus_ma_highlight.png/250px-Saugus_ma_highlight.png", "name": "saugus", "gov_type": "representative town meeting", "vote_percentages": {"% Cahill": 11.93607121, "% Patrick": 31.00343921, "% Baker": 56.01861218, "% Stein": 1.041877402}, "local_aid_2008": 4986749.783}