{"victory_district": 7, "county": "Hampden", "delta_local_aid": -7291.851126, "state_senator": "Donald F. Humason, Jr. ( R )", "established": 1810, "votes": {"Patrick": 70, "Baker": 119, "Total": 209, "Stein": 9, "Cahill": 11}, "unemployment_percentage": 7.2, "registered_voters": {"Unenrolled": 217, "Green-Rainbow": 0, "Republican": 85, "Democrat": 65, "Total": 367}, "local_aid_2013": 15633.0, "percent_registered_unenrolled": 59.1280654, "media_market": "Springfield", "delta_local_aid_per_capita": -15.03474459, "unemployment_total": 19, "unemployment_difference_from_MA_average": 0.5, "registered_percentages": {"% Republican": 23.16076294, "% Democrat": 17.71117166, "% Green-Rainbow": 0.0, "% Unenrolled": 59.1280654}, "percent_registered_republicans": 23.16076294, "delta_local_aid_percentage": -34.73798831, "slug": "tolland", "federal_reps": "Richard Neal (D)", "population": 485, "image_link": "http://upload.wikimedia.org/wikipedia/commons/thumb/9/94/Tolland_ma_highlight.png/250px-Tolland_ma_highlight.png", "name": "tolland", "gov_type": "open town meeting", "vote_percentages": {"% Cahill": 5.263157895, "% Patrick": 33.49282297, "% Baker": 56.93779904, "% Stein": 4.306220096}, "local_aid_2008": 22924.85113}