{"established": 1771, "votes": {"Patrick": 246, "Baker": 92, "Total": 375, "Stein": 11, "Cahill": 26}, "name": "windsor", "gov_type": "open town meeting", "unemployment_percentage": 6.9, "image_link": "http://upload.wikimedia.org/wikipedia/commons/thumb/6/69/Windsor_MA_lg.PNG/250px-Windsor_MA_lg.PNG", "delta_local_aid": -46598.45088, "unemployment_total": 35, "registered_voters": {"Unenrolled": 435, "Green-Rainbow": 2, "Republican": 58, "Democrat": 168, "Total": 664}, "county": "Berkshire", "local_aid_2013": 87837.0, "vote_percentages": {"% Cahill": 6.933333333, "% Patrick": 65.6, "% Baker": 24.53333333, "% Stein": 2.933333333}, "unemployment_difference_from_MA_average": 0.2, "local_aid_2008": 134435.4509, "registered_percentages": {"% Republican": 8.734939759, "% Democrat": 25.30120482, "% Green-Rainbow": 0.301204819, "% Unenrolled": 65.51204819}, "percent_registered_republicans": 8.734939759, "percent_registered_unenrolled": 65.51204819, "delta_local_aid_percentage": -37.85568129, "slug": "windsor", "delta_local_aid_per_capita": -51.83364947, "population": 899}